zxx/File.py
zxx/Highlight.py
zxx/__init__.py
zxx/options.py
zxx/tools.py
zxx-1.2.0.dist-info/licenses/LICENSE
zxx-1.2.0.dist-info/METADATA
zxx-1.2.0.dist-info/WHEEL
zxx-1.2.0.dist-info/top_level.txt
zxx-1.2.0.dist-info/RECORD
