Metadata-Version: 2.4
Name: zxx
Version: 1.2.0
Summary: A Python package developed by “Zheng-Xin-She” (formerly “Zheng-Xin-Xin”) Women’s Football Team at Peking University, mainly used for editing game highlights.
Home-page: https://pypi.org/project/zxx
Author: Yifan Zhang
Author-email: zyfcode@outlook.com
Classifier: Programming Language :: Python :: 3
Classifier: License :: OSI Approved :: GNU General Public License v3 (GPLv3)
Classifier: Operating System :: OS Independent
Requires-Python: >=3.10
License-File: LICENSE
Dynamic: license-file
